cfe/__init__.py
cfe/__main__.py
cfe/paths.py
cfe/drive_api/__init__.py
cfe/drive_api/auth.py
cfe/drive_api/client_secret.json
cfe/drive_api/func.py
cfe/drive_api/settings.yaml
cfe/vault/__init__.py
cfe/vault/crypto.py
cfe/vault/storage.py
cf_encryptor-0.1.8.dist-info/LICENSE
cf_encryptor-0.1.8.dist-info/METADATA
cf_encryptor-0.1.8.dist-info/WHEEL
cf_encryptor-0.1.8.dist-info/entry_points.txt
cf_encryptor-0.1.8.dist-info/top_level.txt
cf_encryptor-0.1.8.dist-info/RECORD
